CHANGELOG.rst
MANIFEST.in
README.rst
setup.cfg
setup.py
rt/__init__.py
rt.commands.egg-info/PKG-INFO
rt.commands.egg-info/SOURCES.txt
rt.commands.egg-info/dependency_links.txt
rt.commands.egg-info/entry_points.txt
rt.commands.egg-info/namespace_packages.txt
rt.commands.egg-info/not-zip-safe
rt.commands.egg-info/top_level.txt
rt/commands/__init__.py
rt/commands/buildout_components.py
rt/commands/project.py
rt/commands/components/__init__.py
rt/commands/components/plone.py