Metadata-Version: 1.0
Name: rt.commands
Version: 0.1.4
Summary: Fabric scripts for RT
Home-page: http://www.redturtle.it
Author: RedTurtle developers
Author-email: sviluppo@redturtle.it
License: GPL
Platform: UNKNOWN
